LICENSE
README.md
setup.cfg
setup.py
neuropathicalz/__init__.py
neuropathicalz/main.py
neuropathicalz.egg-info/PKG-INFO
neuropathicalz.egg-info/SOURCES.txt
neuropathicalz.egg-info/dependency_links.txt
neuropathicalz.egg-info/requires.txt
neuropathicalz.egg-info/top_level.txt